SpanishWF/__init__.py
SpanishWF/parameters.py
SpanishWF/specificpredictions.py
SpanishWF/swfunctions.py
SpanishWF/urls.py
SpainWF-0.1.0.dist-info/LICENSE
SpainWF-0.1.0.dist-info/METADATA
SpainWF-0.1.0.dist-info/WHEEL
SpainWF-0.1.0.dist-info/top_level.txt
SpainWF-0.1.0.dist-info/RECORD
