Metadata-Version: 2.1
Name: SpainWF
Version: 0.1.0
Summary: Consulta Predicciones Meteorologicas AEMET
Home-page: https://github.com/Miguel-bc/SpanishWF.git
Author: Miguel Blaya
Author-email: miguel.blaya@gmail.com
Classifier: Programming Language :: Python :: 3
Classifier: License :: OSI Approved :: MIT License
Classifier: Operating System :: OS Independent
Requires-Python: >=3.6
License-File: LICENSE
